{
    "version": "0.1.1",
    "architecture": {
        "64bit": {
            "url": "https://github.com/Crisbr10/sequoia/releases/download/v0.1.1/sequoia_0.1.1_windows_amd64.zip",
            "bin": [
                "sequoia.exe"
            ],
            "hash": "69a0ff7889bec02ec14d33e7efdd18fdd142960e81bf0afecc3c237f14b9d86d"
        }
    },
    "homepage": "https://github.com/Crisbr10/sequoia",
    "license": "MIT",
    "description": "Multi-agent code audit framework with Go CLI installer and TUI.\nDeploy specialized AI agents to inspect projects from every angle.\n"
}
